[{"timestamp":1601396709009,"files":[{"filename":"bundle.*****.esm.js","previous":7621,"size":7621,"diff":0},{"filename":"polyfills.*****.esm.js","previous":2015,"size":2015,"diff":0},{"filename":"route-home.chunk.6231b.css","previous":368,"size":368,"diff":0},{"filename":"route-home.chunk.*****.esm.js","previous":20388,"size":19902,"diff":-486},{"filename":"sw-esm.js","previous":8474,"size":8474,"diff":0},{"filename":"sw.js","previous":8471,"size":8471,"diff":0},{"filename":"index.html","previous":881,"size":2129,"diff":1248},{"filename":"sw-debug.js","previous":397,"size":397,"diff":0},{"filename":"polyfills.694cb.js","previous":2013,"size":2013,"diff":0},{"filename":"bundle.66354.css","previous":683,"size":683,"diff":0},{"filename":"bundle.0256c.js","previous":7587,"size":0,"diff":-7587},{"filename":"route-home.chunk.5f38c.js","previous":20423,"size":0,"diff":-20423},{"filename":"bundle.a3ae2.js","previous":0,"size":7586,"diff":7586},{"filename":"route-home.chunk.91344.js","previous":0,"size":19934,"diff":19934}]},{"timestamp":1601396664194,"files":[{"filename":"bundle.*****.esm.js","previous":7621,"size":7621,"diff":0},{"filename":"polyfills.*****.esm.js","previous":2015,"size":2015,"diff":0},{"filename":"route-home.chunk.6231b.css","previous":368,"size":368,"diff":0},{"filename":"route-home.chunk.*****.esm.js","previous":20388,"size":20388,"diff":0},{"filename":"sw-esm.js","previous":8474,"size":8474,"diff":0},{"filename":"sw.js","previous":8471,"size":8471,"diff":0},{"filename":"index.html","previous":742,"size":881,"diff":139},{"filename":"sw-debug.js","previous":397,"size":397,"diff":0},{"filename":"polyfills.694cb.js","previous":2013,"size":2013,"diff":0},{"filename":"bundle.66354.css","previous":683,"size":683,"diff":0},{"filename":"bundle.0256c.js","previous":7587,"size":7587,"diff":0},{"filename":"route-home.chunk.5f38c.js","previous":20423,"size":20423,"diff":0}]},{"timestamp":1601396645417,"files":[{"filename":"bundle.*****.esm.js","previous":7621,"size":7621,"diff":0},{"filename":"polyfills.*****.esm.js","previous":2015,"size":2015,"diff":0},{"filename":"route-home.chunk.6231b.css","previous":368,"size":368,"diff":0},{"filename":"route-home.chunk.*****.esm.js","previous":20388,"size":20388,"diff":0},{"filename":"sw-esm.js","previous":8474,"size":8474,"diff":0},{"filename":"sw.js","previous":8471,"size":8471,"diff":0},{"filename":"index.html","previous":1088,"size":742,"diff":-346},{"filename":"sw-debug.js","previous":397,"size":397,"diff":0},{"filename":"polyfills.694cb.js","previous":2013,"size":2013,"diff":0},{"filename":"bundle.66354.css","previous":683,"size":683,"diff":0},{"filename":"bundle.0256c.js","previous":7587,"size":7587,"diff":0},{"filename":"route-home.chunk.5f38c.js","previous":20423,"size":20423,"diff":0}]},{"timestamp":1601396630263,"files":[{"filename":"bundle.*****.esm.js","previous":7619,"size":7621,"diff":2},{"filename":"polyfills.*****.esm.js","previous":2015,"size":2015,"diff":0},{"filename":"route-home.chunk.6231b.css","previous":368,"size":368,"diff":0},{"filename":"route-home.chunk.*****.esm.js","previous":20339,"size":20388,"diff":49},{"filename":"sw-esm.js","previous":8474,"size":8474,"diff":0},{"filename":"sw.js","previous":8471,"size":8471,"diff":0},{"filename":"index.html","previous":2289,"size":1088,"diff":-1201},{"filename":"sw-debug.js","previous":397,"size":397,"diff":0},{"filename":"polyfills.694cb.js","previous":2013,"size":2013,"diff":0},{"filename":"bundle.66354.css","previous":683,"size":683,"diff":0},{"filename":"bundle.9bc87.js","previous":7588,"size":0,"diff":-7588},{"filename":"route-home.chunk.f9197.js","previous":20373,"size":0,"diff":-20373},{"filename":"bundle.0256c.js","previous":0,"size":7587,"diff":7587},{"filename":"route-home.chunk.5f38c.js","previous":0,"size":20423,"diff":20423}]},{"timestamp":1601396069045,"files":[{"filename":"bundle.*****.esm.js","previous":7619,"size":7619,"diff":0},{"filename":"polyfills.*****.esm.js","previous":2015,"size":2015,"diff":0},{"filename":"route-home.chunk.6231b.css","previous":368,"size":368,"diff":0},{"filename":"route-home.chunk.*****.esm.js","previous":20339,"size":20339,"diff":0},{"filename":"sw-esm.js","previous":8474,"size":8474,"diff":0},{"filename":"sw.js","previous":8471,"size":8471,"diff":0},{"filename":"index.html","previous":1572,"size":2289,"diff":717},{"filename":"sw-debug.js","previous":397,"size":397,"diff":0},{"filename":"polyfills.694cb.js","previous":2013,"size":2013,"diff":0},{"filename":"bundle.66354.css","previous":683,"size":683,"diff":0},{"filename":"bundle.9bc87.js","previous":7588,"size":7588,"diff":0},{"filename":"route-home.chunk.f9197.js","previous":20373,"size":20373,"diff":0}]},{"timestamp":1601396038005,"files":[{"filename":"bundle.*****.esm.js","previous":7619,"size":7619,"diff":0},{"filename":"polyfills.*****.esm.js","previous":2015,"size":2015,"diff":0},{"filename":"route-home.chunk.6231b.css","previous":368,"size":368,"diff":0},{"filename":"route-home.chunk.*****.esm.js","previous":20339,"size":20339,"diff":0},{"filename":"sw-esm.js","previous":8474,"size":8474,"diff":0},{"filename":"sw.js","previous":8471,"size":8471,"diff":0},{"filename":"index.html","previous":1075,"size":1572,"diff":497},{"filename":"sw-debug.js","previous":397,"size":397,"diff":0},{"filename":"polyfills.694cb.js","previous":2013,"size":2013,"diff":0},{"filename":"bundle.66354.css","previous":683,"size":683,"diff":0},{"filename":"bundle.9bc87.js","previous":7588,"size":7588,"diff":0},{"filename":"route-home.chunk.f9197.js","previous":20373,"size":20373,"diff":0}]},{"timestamp":1601396019522,"files":[{"filename":"bundle.*****.esm.js","previous":7621,"size":7619,"diff":-2},{"filename":"polyfills.*****.esm.js","previous":2015,"size":2015,"diff":0},{"filename":"route-home.chunk.6231b.css","previous":368,"size":368,"diff":0},{"filename":"route-home.chunk.*****.esm.js","previous":20249,"size":20339,"diff":90},{"filename":"sw-esm.js","previous":8474,"size":8474,"diff":0},{"filename":"sw.js","previous":8471,"size":8471,"diff":0},{"filename":"index.html","previous":2026,"size":1075,"diff":-951},{"filename":"sw-debug.js","previous":397,"size":397,"diff":0},{"filename":"route-home.chunk.8f63f.js","previous":20278,"size":0,"diff":-20278},{"filename":"polyfills.694cb.js","previous":2013,"size":2013,"diff":0},{"filename":"bundle.3ba47.css","previous":550,"size":0,"diff":-550},{"filename":"bundle.95880.js","previous":7588,"size":0,"diff":-7588},{"filename":"bundle.66354.css","previous":0,"size":683,"diff":683},{"filename":"bundle.9bc87.js","previous":0,"size":7588,"diff":7588},{"filename":"route-home.chunk.f9197.js","previous":0,"size":20373,"diff":20373}]},{"timestamp":1601393141056,"files":[{"filename":"bundle.*****.esm.js","previous":7621,"size":7621,"diff":0},{"filename":"polyfills.*****.esm.js","previous":2015,"size":2015,"diff":0},{"filename":"route-home.chunk.6231b.css","previous":368,"size":368,"diff":0},{"filename":"route-home.chunk.*****.esm.js","previous":20249,"size":20249,"diff":0},{"filename":"sw-esm.js","previous":8474,"size":8474,"diff":0},{"filename":"sw.js","previous":8471,"size":8471,"diff":0},{"filename":"index.html","previous":749,"size":2026,"diff":1277},{"filename":"sw-debug.js","previous":397,"size":397,"diff":0},{"filename":"route-home.chunk.8f63f.js","previous":20278,"size":20278,"diff":0},{"filename":"polyfills.694cb.js","previous":2013,"size":2013,"diff":0},{"filename":"bundle.3ba47.css","previous":550,"size":550,"diff":0},{"filename":"bundle.95880.js","previous":7588,"size":7588,"diff":0}]},{"timestamp":1601393125241,"files":[{"filename":"bundle.ec402.css","previous":516,"size":0,"diff":-516},{"filename":"bundle.*****.esm.js","previous":7622,"size":7621,"diff":-1},{"filename":"polyfills.*****.esm.js","previous":2015,"size":2015,"diff":0},{"filename":"route-home.chunk.6231b.css","previous":368,"size":368,"diff":0},{"filename":"route-home.chunk.*****.esm.js","previous":20249,"size":20249,"diff":0},{"filename":"sw-esm.js","previous":8474,"size":8474,"diff":0},{"filename":"sw.js","previous":8471,"size":8471,"diff":0},{"filename":"index.html","previous":2060,"size":749,"diff":-1311},{"filename":"sw-debug.js","previous":397,"size":397,"diff":0},{"filename":"route-home.chunk.8f63f.js","previous":20278,"size":20278,"diff":0},{"filename":"bundle.88358.js","previous":7588,"size":0,"diff":-7588},{"filename":"polyfills.694cb.js","previous":2013,"size":2013,"diff":0},{"filename":"bundle.3ba47.css","previous":0,"size":550,"diff":550},{"filename":"bundle.95880.js","previous":0,"size":7588,"diff":7588}]},{"timestamp":1601391332292,"files":[{"filename":"bundle.ec402.css","previous":516,"size":516,"diff":0},{"filename":"bundle.*****.esm.js","previous":7622,"size":7622,"diff":0},{"filename":"polyfills.*****.esm.js","previous":2015,"size":2015,"diff":0},{"filename":"route-home.chunk.6231b.css","previous":368,"size":368,"diff":0},{"filename":"route-home.chunk.*****.esm.js","previous":20249,"size":20249,"diff":0},{"filename":"sw-esm.js","previous":8474,"size":8474,"diff":0},{"filename":"sw.js","previous":8471,"size":8471,"diff":0},{"filename":"index.html","previous":882,"size":2060,"diff":1178},{"filename":"sw-debug.js","previous":397,"size":397,"diff":0},{"filename":"route-home.chunk.8f63f.js","previous":20278,"size":20278,"diff":0},{"filename":"bundle.88358.js","previous":7588,"size":7588,"diff":0},{"filename":"polyfills.694cb.js","previous":2013,"size":2013,"diff":0}]},{"timestamp":1601391314029,"files":[{"filename":"bundle.ec402.css","previous":516,"size":516,"diff":0},{"filename":"bundle.*****.esm.js","previous":7632,"size":7622,"diff":-10},{"filename":"polyfills.*****.esm.js","previous":2026,"size":2015,"diff":-11},{"filename":"route-home.chunk.6231b.css","previous":368,"size":368,"diff":0},{"filename":"route-home.chunk.*****.esm.js","previous":20249,"size":20249,"diff":0},{"filename":"sw-esm.js","previous":8482,"size":8474,"diff":-8},{"filename":"sw.js","previous":8479,"size":8471,"diff":-8},{"filename":"index.html","previous":2061,"size":882,"diff":-1179},{"filename":"sw-debug.js","previous":397,"size":397,"diff":0},{"filename":"route-home.chunk.8f63f.js","previous":20278,"size":20278,"diff":0},{"filename":"bundle.f6fc5.js","previous":7597,"size":0,"diff":-7597},{"filename":"polyfills.e1744.js","previous":2021,"size":0,"diff":-2021},{"filename":"bundle.88358.js","previous":0,"size":7588,"diff":7588},{"filename":"polyfills.694cb.js","previous":0,"size":2013,"diff":2013}]},{"timestamp":1601363757235,"files":[{"filename":"bundle.ec402.css","previous":516,"size":516,"diff":0},{"filename":"bundle.*****.esm.js","previous":7622,"size":7632,"diff":10},{"filename":"polyfills.*****.esm.js","previous":2015,"size":2026,"diff":11},{"filename":"route-home.chunk.6231b.css","previous":368,"size":368,"diff":0},{"filename":"route-home.chunk.*****.esm.js","previous":20249,"size":20249,"diff":0},{"filename":"sw-esm.js","previous":8474,"size":8482,"diff":8},{"filename":"sw.js","previous":8471,"size":8479,"diff":8},{"filename":"polyfills.694cb.js","previous":2013,"size":0,"diff":-2013},{"filename":"index.html","previous":2018,"size":2061,"diff":43},{"filename":"sw-debug.js","previous":397,"size":397,"diff":0},{"filename":"bundle.88358.js","previous":7588,"size":0,"diff":-7588},{"filename":"route-home.chunk.8f63f.js","previous":20278,"size":20278,"diff":0},{"filename":"bundle.f6fc5.js","previous":0,"size":7597,"diff":7597},{"filename":"polyfills.e1744.js","previous":0,"size":2021,"diff":2021}]},{"timestamp":1601363280800,"files":[{"filename":"bundle.ec402.css","previous":516,"size":516,"diff":0},{"filename":"bundle.*****.esm.js","previous":7622,"size":7622,"diff":0},{"filename":"polyfills.*****.esm.js","previous":2015,"size":2015,"diff":0},{"filename":"route-home.chunk.6231b.css","previous":368,"size":368,"diff":0},{"filename":"route-home.chunk.*****.esm.js","previous":20249,"size":20249,"diff":0},{"filename":"sw-esm.js","previous":8474,"size":8474,"diff":0},{"filename":"sw.js","previous":8471,"size":8471,"diff":0},{"filename":"polyfills.694cb.js","previous":2013,"size":2013,"diff":0},{"filename":"index.html","previous":1988,"size":2018,"diff":30},{"filename":"sw-debug.js","previous":397,"size":397,"diff":0},{"filename":"bundle.88358.js","previous":7588,"size":7588,"diff":0},{"filename":"route-home.chunk.8f63f.js","previous":20278,"size":20278,"diff":0}]},{"timestamp":1601363021129,"files":[{"filename":"bundle.ec402.css","previous":516,"size":516,"diff":0},{"filename":"bundle.*****.esm.js","previous":7622,"size":7622,"diff":0},{"filename":"polyfills.*****.esm.js","previous":2015,"size":2015,"diff":0},{"filename":"route-home.chunk.6231b.css","previous":368,"size":368,"diff":0},{"filename":"route-home.chunk.*****.esm.js","previous":20249,"size":20249,"diff":0},{"filename":"sw-esm.js","previous":8474,"size":8474,"diff":0},{"filename":"sw.js","previous":8471,"size":8471,"diff":0},{"filename":"polyfills.694cb.js","previous":2013,"size":2013,"diff":0},{"filename":"index.html","previous":882,"size":1988,"diff":1106},{"filename":"sw-debug.js","previous":397,"size":397,"diff":0},{"filename":"bundle.88358.js","previous":7588,"size":7588,"diff":0},{"filename":"route-home.chunk.8f63f.js","previous":20278,"size":20278,"diff":0}]},{"timestamp":1601362960224,"files":[{"filename":"bundle.ec402.css","previous":516,"size":516,"diff":0},{"filename":"bundle.*****.esm.js","previous":7622,"size":7622,"diff":0},{"filename":"polyfills.*****.esm.js","previous":2015,"size":2015,"diff":0},{"filename":"route-home.chunk.6231b.css","previous":368,"size":368,"diff":0},{"filename":"route-home.chunk.*****.esm.js","previous":20249,"size":20249,"diff":0},{"filename":"sw-esm.js","previous":8474,"size":8474,"diff":0},{"filename":"sw.js","previous":8471,"size":8471,"diff":0},{"filename":"polyfills.694cb.js","previous":2013,"size":2013,"diff":0},{"filename":"index.html","previous":2072,"size":882,"diff":-1190},{"filename":"sw-debug.js","previous":397,"size":397,"diff":0},{"filename":"bundle.88358.js","previous":7588,"size":7588,"diff":0},{"filename":"route-home.chunk.8f63f.js","previous":20278,"size":20278,"diff":0}]},{"timestamp":1601362190713,"files":[{"filename":"bundle.ec402.css","previous":516,"size":516,"diff":0},{"filename":"bundle.*****.esm.js","previous":7551,"size":7622,"diff":71},{"filename":"polyfills.*****.esm.js","previous":2015,"size":2015,"diff":0},{"filename":"route-home.chunk.6231b.css","previous":368,"size":368,"diff":0},{"filename":"route-home.chunk.*****.esm.js","previous":20249,"size":20249,"diff":0},{"filename":"sw-esm.js","previous":8474,"size":8474,"diff":0},{"filename":"sw.js","previous":8471,"size":8471,"diff":0},{"filename":"bundle.308c3.js","previous":7528,"size":0,"diff":-7528},{"filename":"polyfills.694cb.js","previous":2013,"size":2013,"diff":0},{"filename":"route-home.chunk.bbf27.js","previous":20278,"size":0,"diff":-20278},{"filename":"index.html","previous":2014,"size":2072,"diff":58},{"filename":"sw-debug.js","previous":397,"size":397,"diff":0},{"filename":"bundle.88358.js","previous":0,"size":7588,"diff":7588},{"filename":"route-home.chunk.8f63f.js","previous":0,"size":20278,"diff":20278}]},{"timestamp":1601362118461,"files":[{"filename":"ssr-build/ssr-bundle.0984c.css","previous":917,"size":0,"diff":-917},{"filename":"ssr-build/ssr-bundle.js","previous":22238,"size":0,"diff":-22238},{"filename":"bundle.ec402.css","previous":0,"size":516,"diff":516},{"filename":"bundle.*****.esm.js","previous":0,"size":7551,"diff":7551},{"filename":"polyfills.*****.esm.js","previous":0,"size":2015,"diff":2015},{"filename":"route-home.chunk.6231b.css","previous":0,"size":368,"diff":368},{"filename":"route-home.chunk.*****.esm.js","previous":0,"size":20249,"diff":20249},{"filename":"sw-esm.js","previous":0,"size":8474,"diff":8474},{"filename":"sw.js","previous":0,"size":8471,"diff":8471},{"filename":"bundle.308c3.js","previous":0,"size":7528,"diff":7528},{"filename":"polyfills.694cb.js","previous":0,"size":2013,"diff":2013},{"filename":"route-home.chunk.bbf27.js","previous":0,"size":20278,"diff":20278},{"filename":"index.html","previous":0,"size":2014,"diff":2014},{"filename":"sw-debug.js","previous":0,"size":397,"diff":397}]}]
